cppcheck/_version.py
cppcheck/__main__.py
cppcheck/py.typed
cppcheck/_version.pyi
cppcheck/__init__.py
cppcheck/Cppcheck/cppcheck
cppcheck/Cppcheck/addons/namingng.py
cppcheck/Cppcheck/addons/naming.py
cppcheck/Cppcheck/addons/cppcheck.py
cppcheck/Cppcheck/addons/cppcheckdata.py
cppcheck/Cppcheck/addons/runaddon.py
cppcheck/Cppcheck/addons/misra.py
cppcheck/Cppcheck/addons/__init__.py
cppcheck/Cppcheck/addons/misra_9.py
cppcheck/Cppcheck/addons/y2038.py
cppcheck/Cppcheck/addons/misc.py
cppcheck/Cppcheck/addons/findcasts.py
cppcheck/Cppcheck/addons/threadsafety.py
cppcheck/Cppcheck/platforms/msp430_eabi_large_datamodel.xml
cppcheck/Cppcheck/platforms/unix64-unsigned.xml
cppcheck/Cppcheck/platforms/arm32-wchar_t4.xml
cppcheck/Cppcheck/platforms/pic8-enhanced.xml
cppcheck/Cppcheck/platforms/pic8.xml
cppcheck/Cppcheck/platforms/pic16.xml
cppcheck/Cppcheck/platforms/mips32.xml
cppcheck/Cppcheck/platforms/arm32-wchar_t2.xml
cppcheck/Cppcheck/platforms/cray_sv1.xml
cppcheck/Cppcheck/platforms/arm64-wchar_t4.xml
cppcheck/Cppcheck/platforms/avr8.xml
cppcheck/Cppcheck/platforms/unix32-unsigned.xml
cppcheck/Cppcheck/platforms/elbrus-e1cp.xml
cppcheck/Cppcheck/platforms/aix_ppc64.xml
cppcheck/Cppcheck/platforms/arm64-wchar_t2.xml
cppcheck/Cppcheck/cfg/microsoft_atl.cfg
cppcheck/Cppcheck/cfg/wxsvg.cfg
cppcheck/Cppcheck/cfg/cppcheck-lib.cfg
cppcheck/Cppcheck/cfg/vcl.cfg
cppcheck/Cppcheck/cfg/cairo.cfg
cppcheck/Cppcheck/cfg/gtk.cfg
cppcheck/Cppcheck/cfg/opencv2.cfg
cppcheck/Cppcheck/cfg/pcre.cfg
cppcheck/Cppcheck/cfg/libsigc++.cfg
cppcheck/Cppcheck/cfg/cppunit.cfg
cppcheck/Cppcheck/cfg/wxwidgets.cfg
cppcheck/Cppcheck/cfg/protobuf.cfg
cppcheck/Cppcheck/cfg/libcerror.cfg
cppcheck/Cppcheck/cfg/dpdk.cfg
cppcheck/Cppcheck/cfg/opengl.cfg
cppcheck/Cppcheck/cfg/embedded_sql.cfg
cppcheck/Cppcheck/cfg/sqlite3.cfg
cppcheck/Cppcheck/cfg/microsoft_unittest.cfg
cppcheck/Cppcheck/cfg/wxsqlite3.cfg
cppcheck/Cppcheck/cfg/motif.cfg
cppcheck-1.5.0.dist-info/WHEEL
cppcheck-1.5.0.dist-info/RECORD
cppcheck-1.5.0.dist-info/entry_points.txt
cppcheck-1.5.0.dist-info/METADATA
cppcheck-1.5.0.dist-info/licenses/LICENSE
