Metadata-Version: 2.1
Name: cppcheck
Version: 1.5.0
Summary: Package cppcheck as a python wheel.
Author-Email: "l.feng" <msclock@126.com>
License: Apache-2.0
Classifier: Intended Audience :: Science/Research
Classifier: Intended Audience :: Developers
Classifier: License :: OSI Approved :: Apache Software License
Classifier: Operating System :: OS Independent
Classifier: Programming Language :: Python
Classifier: Programming Language :: Python :: 3
Classifier: Programming Language :: Python :: 3 :: Only
Classifier: Programming Language :: Python :: 3.7
Classifier: Programming Language :: Python :: 3.8
Classifier: Programming Language :: Python :: 3.9
Classifier: Programming Language :: Python :: 3.10
Classifier: Programming Language :: Python :: 3.11
Classifier: Programming Language :: Python :: 3.12
Classifier: Programming Language :: Python :: 3.13
Classifier: Topic :: Scientific/Engineering
Classifier: Typing :: Typed
Project-URL: Homepage, https://github.com/msclock/cppcheck-wheel
Project-URL: Bug Tracker, https://github.com/msclock/cppcheck-wheel/issues
Project-URL: Discussions, https://github.com/msclock/cppcheck-wheel/discussions
Project-URL: Changelog, https://github.com/msclock/cppcheck-wheel/releases
Requires-Python: >=3.7
Requires-Dist: typing-extensions>=3.10.0; python_version < "3.9"
Requires-Dist: importlib_metadata>=1.4
Provides-Extra: test
Requires-Dist: pytest>=6; extra == "test"
Requires-Dist: pytest-cov>=3; extra == "test"
Provides-Extra: dev
Requires-Dist: pytest>=6; extra == "dev"
Requires-Dist: pytest-cov>=3; extra == "dev"
Provides-Extra: docs
Requires-Dist: sphinx>=7.0; extra == "docs"
Requires-Dist: myst_parser>=0.13; extra == "docs"
Requires-Dist: sphinx_copybutton; extra == "docs"
Requires-Dist: sphinx_autodoc_typehints; extra == "docs"
Requires-Dist: furo>=2023.08.17; extra == "docs"
